pydantic_prompter-0.1.32.dist-info/METADATA
pydantic_prompter-0.1.32.dist-info/WHEEL
pydantic_prompter-0.1.32.dist-info/licenses/LICENSE
pydantic_prompter/__init__.py
pydantic_prompter/annotation_parser.py
pydantic_prompter/common.py
pydantic_prompter/exceptions.py
pydantic_prompter/llm_providers/__init__.py
pydantic_prompter/llm_providers/base.py
pydantic_prompter/llm_providers/bedrock_anthropic.py
pydantic_prompter/llm_providers/bedrock_base.py
pydantic_prompter/llm_providers/bedrock_cohere.py
pydantic_prompter/llm_providers/bedrock_llama2.py
pydantic_prompter/llm_providers/cohere.py
pydantic_prompter/llm_providers/openai.py
pydantic_prompter/prompt_templates/pydantic/cohere.jinja
pydantic_prompter/prompt_templates/pydantic/llama2.jinja
pydantic_prompter/prompt_templates/simple/cohere.jinja
pydantic_prompter/prompt_templates/simple/llama2.jinja
pydantic_prompter/prompter.py
pydantic_prompter/settings.py
pydantic_prompter-0.1.32.dist-info/RECORD
