Metadata-Version: 2.1
Name: pydantic-prompter
Version: 0.1.32
Summary: Pydantic Prompter is a lightweight utility designed to facilitate the construction of prompts using YAML and generate Pydantic objects as outputs.
Author-Email: Ofer Helman <helmanofer@gmail.com>
License: MIT
Project-URL: Source, https://github.com/helmanofer/pydantic-prompter
Project-URL: Docs, https://helmanofer.github.io/pydantic-prompter/
Requires-Python: >=3.9
Requires-Dist: jinja2>=3.1.2
Requires-Dist: pyyaml>=6.0.1
Requires-Dist: retry>=0.9.2
Requires-Dist: pydantic>2.0.0
Requires-Dist: pydantic-settings>=2.1.0
Requires-Dist: openai>=1.6.1; extra == "openai"
Requires-Dist: botocore>=1.34.11; extra == "bedrock"
Requires-Dist: boto3>=1.34.11; extra == "bedrock"
Requires-Dist: awscli>=1.32.11; extra == "bedrock"
Requires-Dist: fix_busted_json>0.0.18; extra == "bedrock"
Requires-Dist: cohere>=4.46; extra == "chere"
Provides-Extra: openai
Provides-Extra: bedrock
Provides-Extra: chere
